dalex/__init__.py
dalex/_explanation.py
dalex/_global_checks.py
dalex/_global_utils.py
dalex/_theme.py
dalex/documentation.md
dalex/_explainer/__init__.py
dalex/_explainer/checks.py
dalex/_explainer/helper.py
dalex/_explainer/object.py
dalex/_explainer/utils.py
dalex/_explainer/yhat.py
dalex/arena/__init__.py
dalex/arena/_option_base.py
dalex/arena/_plot_container.py
dalex/arena/_plots_manager.py
dalex/arena/_resource.py
dalex/arena/_resource_manager.py
dalex/arena/object.py
dalex/arena/params.py
dalex/arena/server.py
dalex/arena/static.py
dalex/arena/plots/__init__.py
dalex/arena/plots/_accumulated_dependence_container.py
dalex/arena/plots/_break_down_container.py
dalex/arena/plots/_ceteris_paribus_container.py
dalex/arena/plots/_fairness_check_container.py
dalex/arena/plots/_feature_importance_container.py
dalex/arena/plots/_metrics_container.py
dalex/arena/plots/_partial_dependence_container.py
dalex/arena/plots/_roc_container.py
dalex/arena/plots/_shapley_values_container.py
dalex/arena/plots/_shapley_values_dependence_container.py
dalex/arena/plots/_shapley_values_variable_importance_container.py
dalex/arena/plots/_variable_against_another_container.py
dalex/arena/plots/_variable_distribution_container.py
dalex/arena/resources/__init__.py
dalex/arena/resources/_dataset_shapley_values_resource.py
dalex/arena/resources/_shapley_values_resource.py
dalex/aspect/__init__.py
dalex/aspect/checks.py
dalex/aspect/object.py
dalex/aspect/plot.py
dalex/aspect/utils.py
dalex/aspect/_model_aspect_importance/__init__.py
dalex/aspect/_model_aspect_importance/checks.py
dalex/aspect/_model_aspect_importance/object.py
dalex/aspect/_model_aspect_importance/plot.py
dalex/aspect/_model_triplot/__init__.py
dalex/aspect/_model_triplot/checks.py
dalex/aspect/_model_triplot/object.py
dalex/aspect/_model_triplot/plot.py
dalex/aspect/_model_triplot/utils.py
dalex/aspect/_predict_aspect_importance/__init__.py
dalex/aspect/_predict_aspect_importance/checks.py
dalex-1.8.0.dist-info/licenses/LICENSE
dalex-1.8.0.dist-info/METADATA
dalex-1.8.0.dist-info/WHEEL
dalex-1.8.0.dist-info/top_level.txt
dalex-1.8.0.dist-info/RECORD
