Metadata-Version: 2.4
Name: dalex
Version: 1.8.0
Summary: Responsible Machine Learning in Python
Home-page: https://dalex.drwhy.ai/
Author: Przemyslaw Biecek
Author-email: przemyslaw.biecek@gmail.com
Maintainer: Hubert Baniecki
Maintainer-email: hbaniecki@gmail.com
Project-URL: Documentation, https://dalex.drwhy.ai/python/
Project-URL: Code, https://github.com/ModelOriented/DALEX/tree/master/python/dalex
Project-URL: Issue tracker, https://github.com/ModelOriented/DALEX/issues
Classifier: Development Status :: 5 - Production/Stable
Classifier: Topic :: Scientific/Engineering
Classifier: Topic :: Scientific/Engineering :: Artificial Intelligence
Classifier: Programming Language :: Python :: 3
Classifier: Programming Language :: Python :: 3.9
Classifier: Programming Language :: Python :: 3.10
Classifier: Programming Language :: Python :: 3.11
Classifier: Programming Language :: Python :: 3.12
Classifier: Programming Language :: Python :: 3.13
Classifier: License :: OSI Approved
Classifier: License :: OSI Approved :: GNU General Public License v3 (GPLv3)
Classifier: Operating System :: OS Independent
Requires-Python: >=3.9
License-File: LICENSE
Requires-Dist: setuptools
Requires-Dist: packaging
Requires-Dist: pandas<3.0.0,>=1.5.3
Requires-Dist: numpy>=1.23.5
Requires-Dist: scipy>=1.6.3
Requires-Dist: plotly>=6.0.0
Requires-Dist: tqdm>=4.61.2
Provides-Extra: full
Requires-Dist: lime>=0.2.0.1; extra == "full"
Requires-Dist: scikit-learn>=0.22.0; extra == "full"
Requires-Dist: statsmodels>=0.11.1; extra == "full"
Requires-Dist: shap>=0.35.0; extra == "full"
Requires-Dist: flask>=1.1.2; extra == "full"
Requires-Dist: flask_cors>=3.0.8; extra == "full"
Requires-Dist: requests>=2.24.0; extra == "full"
Requires-Dist: kaleido>=0.2.1; extra == "full"
Requires-Dist: ipywidgets>=7.6.3; extra == "full"
Dynamic: author
Dynamic: author-email
Dynamic: classifier
Dynamic: description
Dynamic: description-content-type
Dynamic: home-page
Dynamic: license-file
Dynamic: maintainer
Dynamic: maintainer-email
Dynamic: project-url
Dynamic: provides-extra
Dynamic: requires-dist
Dynamic: requires-python
Dynamic: summary
